khmernames/__init__.py
khmernames/generator.py
khmernames-0.7.dist-info/METADATA
khmernames-0.7.dist-info/WHEEL
khmernames-0.7.dist-info/top_level.txt
khmernames-0.7.dist-info/RECORD
