Metadata-Version: 2.4
Name: khmernames
Version: 0.7
Summary: Pro version: Generate unlimited Khmer names without duplicates
Home-page: https://github.com/sammykh/khmernames
Author: Dev by Sammy KH
Author-email: sammytoolsvplus@gmail.com
License: MIT
Keywords: khmer names generator unlimited no-duplicate
Classifier: Development Status :: 5 - Production/Stable
Classifier: Intended Audience :: Developers
Classifier: Topic :: Software Development :: Libraries
Classifier: Programming Language :: Python :: 3
Classifier: Programming Language :: Python :: 3.8
Classifier: License :: OSI Approved :: MIT License
Classifier: Operating System :: OS Independent
Requires-Python: >=3.6
Dynamic: author
Dynamic: author-email
Dynamic: classifier
Dynamic: description
Dynamic: description-content-type
Dynamic: home-page
Dynamic: keywords
Dynamic: license
Dynamic: requires-python
Dynamic: summary
